gemini_search_mcp/__init__.py
gemini_search_mcp/__main__.py
gemini_search_mcp/cli.py
gemini_search_mcp/config.py
gemini_search_mcp/document_answer.py
gemini_search_mcp/document_pipeline.py
gemini_search_mcp/google_client.py
gemini_search_mcp/image_captioner.py
gemini_search_mcp/markdown_rewriter.py
gemini_search_mcp/pdf_converter.py
gemini_search_mcp/server.py
gemini_search_mcp/web_search.py
gemini_search_mcp-0.3.1.dist-info/licenses/LICENSE
gemini_search_mcp-0.3.1.dist-info/METADATA
gemini_search_mcp-0.3.1.dist-info/WHEEL
gemini_search_mcp-0.3.1.dist-info/entry_points.txt
gemini_search_mcp-0.3.1.dist-info/top_level.txt
gemini_search_mcp-0.3.1.dist-info/RECORD
