Metadata-Version: 2.4
Name: gemini-search-mcp
Version: 0.3.1
Summary: MCP server that exposes Gemini web search and document question answering tools.
Author: Gemini Search Team
License: MIT
Project-URL: Homepage, https://github.com/MIMICLab/GeminiSearchMCP
Project-URL: Repository, https://github.com/MIMICLab/GeminiSearchMCP
Project-URL: Issues, https://github.com/MIMICLab/GeminiSearchMCP/issues
Keywords: mcp,gemini,search,google,ai,model-context-protocol
Classifier: Development Status :: 4 - Beta
Classifier: Intended Audience :: Developers
Classifier: License :: OSI Approved :: MIT License
Classifier: Programming Language :: Python :: 3
Classifier: Programming Language :: Python :: 3.9
Classifier: Programming Language :: Python :: 3.10
Classifier: Programming Language :: Python :: 3.11
Classifier: Programming Language :: Python :: 3.12
Classifier: Operating System :: OS Independent
Classifier: Topic :: Software Development :: Libraries :: Python Modules
Requires-Python: >=3.9
License-File: LICENSE
Requires-Dist: mcp>=0.4.0
Requires-Dist: google-genai>=0.3.0
Requires-Dist: opendataloader-pdf>=0.5.0
Requires-Dist: pydantic>=2.6.0
Requires-Dist: markdown>=3.5.0
Requires-Dist: pillow>=10.0.0
Requires-Dist: tomli>=2.0.1
Requires-Dist: tomli-w>=1.0.0
Dynamic: license-file
